COPYING
ChangeLog
MANIFEST.in
NEWS
README
release.py
setup.cfg
setup.py
test/test_auth.py
test/test_client.py
test/test_exc.py
u2fval_client/__init__.py
u2fval_client/auth.py
u2fval_client/client.py
u2fval_client/exc.py
u2fval_client.egg-info/PKG-INFO
u2fval_client.egg-info/SOURCES.txt
u2fval_client.egg-info/dependency_links.txt
u2fval_client.egg-info/requires.txt
u2fval_client.egg-info/top_level.txt